Workbook

Sheet 书目汇总
A1: 序号 | B1: 类别 | C1: 相关度 | D1: 书名 | E1: 副标题 | F1: 中文简介 | G1: 作者/编者 | H1: 丛书 | I1: 出版社 | J1: 版权年 | K1: 在线出版日期 | L1: 版次 | M1: 页数 | N1: 语言 | O1: eBook ISBN | P1: 印刷版 ISBN | Q1: DOI | R1: 书页链接 | S1: PDF 全书下载 | T1: 访问量 | U1: Springer 主题 | V1: 状态
A2: 1 | B2: 骨科·骨折·关节 | C2: 核心 | D2: Shoulder Fractures in Context | E2: Controversies in Orthopaedic Surgery | F2: 肱骨近端骨折专著：流行病学、形态与分型、历史沿革，并基于临床试验证据讨论手术与保守治疗之争（锁定钢板、反肩置换等）。 | G2: 著：Stig Brorson | I2: Springer Cham | J2: 2025 | K2: 15 July 2025 | L2: 1 | M2: XXIII, 185 | N2: 英文 | O2: 978-3-031-93604-3 | P2: 978-3-031-93603-6 | Q2: 10.1007/978-3-031-93604-3 | R2: https://link.springer.com/book/10.1007/978-3-031-93604-3 | S2: https://link.springer.com/content/pdf/10.1007/978-3-031-93604-3.pdf | T2: 58k | U2: Surgical Orthopedics; Imaging / Radiology | V2: 已上线
A3: 2 | B3: 骨科·骨折·关节 | C3: 核心 | D3: Fragility Fracture and Orthogeriatric Nursing | E3: Holistic Care and Management of the Fragility Fracture and Orthogeriatric Patient | F3: 脆性骨折与骨科老年护理（第2版）：老年脆性骨折患者评估、护理、康复与二级预防，覆盖急性期至居家各场景。 | G3: 编：Karen Hertz, Julie Santy-Tomlinson | H3: Perspectives in Nursing Management and Care for Older Adults | I3: Springer Cham | J3: 2024 | K3: 08 November 2023 | L3: 2 | M3: XX, 307 | N3: 英文 | O3: 978-3-031-33484-9 | P3: 978-3-031-33483-2 | Q3: 10.1007/978-3-031-33484-9 | R3: https://link.springer.com/book/10.1007/978-3-031-33484-9 | S3: https://link.springer.com/content/pdf/10.1007/978-3-031-33484-9.pdf | T3: 192k | U3: Nursing Management; Geriatrics/Gerontology; Orthopedics | V3: 已上线
A4: 3 | B4: 骨科·骨折·关节 | C4: 核心 | D4: Orthogeriatrics | E4: The Management of Older Patients with Fragility Fractures | F4: 骨科老年医学（第2版）：脆性骨折（尤其髋部骨折）的多学科管理，含围手术期、麻醉、康复与二级预防，由 Fragility Fracture Network 支持。 | G4: 编：Paolo Falaschi, David Marsh | H4: Practical Issues in Geriatrics | I4: Springer Cham | J4: 2021 | K4: 20 August 2020 | L4: 2 | M4: VIII, 357 | N4: 英文 | O4: 978-3-030-48126-1 | P4: 978-3-030-48125-4 | Q4: 10.1007/978-3-030-48126-1 | R4: https://link.springer.com/book/10.1007/978-3-030-48126-1 | S4: https://link.springer.com/content/pdf/10.1007/978-3-030-48126-1.pdf | T4: 656k | U4: Geriatrics/Gerontology; Orthopedics; Anesthesiology; Emergency Medicine; Nursing | V4: 已上线
A5: 4 | B5: 骨科·骨折·关节 | C5: 核心 | D5: Personalized Hip and Knee Joint Replacement | F5: 个性化髋、膝关节置换：运动学对线、个体化假体定位的手术技术、植入物与导航/机器人技术。 | G5: 编：Charles Rivière, Pascal-André Vendittoli | I5: Springer Cham | J5: 2020 | K5: 30 June 2020 | L5: 1 | M5: XVI, 350 | N5: 英文 | O5: 978-3-030-24243-5 | P5: 978-3-030-24245-9 | Q5: 10.1007/978-3-030-24243-5 | R5: https://link.springer.com/book/10.1007/978-3-030-24243-5 | S5: https://link.springer.com/content/pdf/10.1007/978-3-030-24243-5.pdf | T5: 525k | U5: Surgical Orthopedics | V5: 已上线
A6: 5 | B6: 骨科·骨折·关节 | C6: 核心 | D6: Fragility Fracture Nursing | E6: Holistic Care and Management of the Orthogeriatric Patient | F6: 上书第1版：脆性骨折老年患者的整体护理与管理。 | G6: 编：Karen Hertz, Julie Santy-Tomlinson | H6: Perspectives in Nursing Management and Care for Older Adults | I6: Springer Cham | J6: 2018 | K6: 15 June 2018 | L6: 1 | M6: XX, 158 | N6: 英文 | O6: 978-3-319-76681-2 | Q6: 10.1007/978-3-319-76681-2 | R6: https://link.springer.com/book/10.1007/978-3-319-76681-2 | S6: https://link.springer.com/content/pdf/10.1007/978-3-319-76681-2.pdf | T6: 318k | U6: Nursing Management; Geriatrics/Gerontology; Orthopedics | V6: 已上线
A7: 6 | B7: 骨科·骨折·关节 | C7: 核心 | D7: White Paper on Joint Replacement | E7: Status of Hip and Knee Arthroplasty Care in Germany | F7: 德国髋膝关节置换白皮书（英文版）：适应证、手术量、质量与卫生经济学现状。 | G7: 编：Hans-Holger Bleß, Miriam Kip | I7: Springer Berlin, Heidelberg | J7: 2018 | K7: 03 November 2017 | L7: 1 | M7: XII, 135 | N7: 英文 | O7: 978-3-662-55918-5 | P7: 978-3-662-55917-8 | Q7: 10.1007/978-3-662-55918-5 | R7: https://link.springer.com/book/10.1007/978-3-662-55918-5 | S7: https://link.springer.com/content/pdf/10.1007/978-3-662-55918-5.pdf | T7: 37k | U7: Orthopedics; Surgery | V7: 已上线
A8: 7 | B8: 骨科·骨折·关节 | C8: 核心 | D8: Weißbuch Gelenkersatz | E8: Versorgungssituation endoprothetischer Hüft- und Knieoperationen in Deutschland | F8: 上书德文原版（Weißbuch Gelenkersatz）。 | G8: 编：H.-H. Bleß, M. Kip | I8: Springer Berlin, Heidelberg | J8: 2017 | K8: 30 August 2016 | L8: 1 | M8: XII, 142 | N8: 德文 | O8: 978-3-662-53260-7 | P8: 978-3-662-52904-1 | Q8: 10.1007/978-3-662-53260-7 | R8: https://link.springer.com/book/10.1007/978-3-662-53260-7 | S8: https://link.springer.com/content/pdf/10.1007/978-3-662-53260-7.pdf | T8: 55k | U8: Orthopedics; Surgery | V8: 已上线
A9: 8 | B9: 创伤医学 | C9: 核心 | D9: Compartment Syndrome | E9: A Guide to Diagnosis and Management | F9: 骨筋膜室综合征：病理生理、诊断标准、压力监测、上下肢筋膜切开术，含儿童与多发伤患者及法律问题。 | G9: 编：Cyril Mauffrey, David J. Hak, Murphy P. Martin III | I9: Springer Cham | J9: 2019 | K9: 02 September 2019 | L9: 1 | M9: XIII, 181 | N9: 英文 | O9: 978-3-030-22331-1 | P9: 978-3-030-22330-4 | Q9: 10.1007/978-3-030-22331-1 | R9: https://link.springer.com/book/10.1007/978-3-030-22331-1 | S9: https://link.springer.com/content/pdf/10.1007/978-3-030-22331-1.pdf | T9: 301k | U9: Orthopedics; Surgery | V9: 已上线
A10: 9 | B10: 创伤医学 | C10: 延伸 | D10: Textbook on Scar Management | E10: State of the Art Management and Emerging Technologies | F10: 瘢痕管理教科书：创伤/烧伤/术后瘢痕的评估、预防与治疗新技术（下载量 240 万+）。 | G10: 编：Luc Téot, Thomas A. Mustoe, Esther Middelkoop, Gerd G. Gauglitz | I10: Springer Cham | J10: 2020 | K10: 07 December 2020 | L10: 1 | M10: XXV, 553 | N10: 英文 | O10: 978-3-030-44766-3 | P10: 978-3-030-44765-6 | Q10: 10.1007/978-3-030-44766-3 | R10: https://link.springer.com/book/10.1007/978-3-030-44766-3 | S10: https://link.springer.com/content/pdf/10.1007/978-3-030-44766-3.pdf | T10: 2.40m | U10: Plastic Surgery; Dermatology; Surgical Oncology | V10: 已上线
A11: 10 | B11: 运动医学·运动损伤 | C11: 核心 | D11: Snow Sports Trauma and Safety | E11: Conference Proceedings of the International Society for Skiing Safety: 21st Volume | F11: 雪上运动创伤与安全（国际滑雪安全学会第21卷会议论文集）：滑雪损伤流行病学、治疗、生物力学与装备/场地预防。 | G11: 编：Irving S. Scher, Richard M. Greenwald, Nicola Petrone | I11: Springer Cham | J11: 2017 | K11: 13 April 2017 | L11: 1 | M11: X, 206 | N11: 英文 | O11: 978-3-319-52755-0 | P11: 978-3-319-52754-3 | Q11: 10.1007/978-3-319-52755-0 | R11: https://link.springer.com/book/10.1007/978-3-319-52755-0 | S11: https://link.springer.com/content/pdf/10.1007/978-3-319-52755-0.pdf | T11: 124k | U11: Sports Medicine; Biomedical Engineering and Bioengineering | V11: 已上线（会议论文集）
A12: 11 | B12: 运动医学·运动科学 | C12: 核心 | D12: Hormones, Metabolism and the Benefits of Exercise | F12: 激素、代谢与运动获益：运动—肌肉—激素—代谢的细胞与分子通路，包括肌因子（myokines）。 | G12: 编：Bruce Spiegelman | H12: Research and Perspectives in Endocrine Interactions | I12: Springer Cham | J12: 2017 | K12: 07 March 2018 | L12: 1 | M12: X, 102 | N12: 英文 | O12: 978-3-319-72790-5 | P12: 978-3-319-72789-9 | Q12: 10.1007/978-3-319-72790-5 | R12: https://link.springer.com/book/10.1007/978-3-319-72790-5 | S12: https://link.springer.com/content/pdf/10.1007/978-3-319-72790-5.pdf | T12: 161k | U12: Molecular Medicine; Health Promotion and Disease Prevention; Endocrinology; Metabolic Diseases | V12: 已上线
A13: 12 | B13: 运动训练·运动科学 | C13: 延伸 | D13: Machine Learning in Sports | E13: Open Approach for Next Play Analytics | F13: 体育中的机器学习：计算机视觉采集比赛数据、预测分析、战术/下一步动作评估与智能体建模。 | G13: 著：Keisuke Fujii | H13: SpringerBriefs in Computer Science | I13: Springer Singapore | J13: 2025 | K13: 10 April 2025 | L13: 1 | M13: XVIII, 127 | N13: 英文 | O13: 978-981-96-1445-5 | P13: 978-981-96-1444-8 | Q13: 10.1007/978-981-96-1445-5 | R13: https://link.springer.com/book/10.1007/978-981-96-1445-5 | S13: https://link.springer.com/content/pdf/10.1007/978-981-96-1445-5.pdf | T13: 50k | U13: Artificial Intelligence; Cyber-physical systems, IoT; Sport Science | V13: 已上线
A14: 13 | B14: 运动训练·运动科学 | C14: 延伸 | D14: Potenziale von Bewegung, Spiel und Sport für ein gesundes Aufwachsen in Deutschland | E14: Ergebnisse aus dem Projekt 'Move for Health' | F14: （德文）运动、游戏与体育对儿童青少年健康成长的作用——“Move for Health”项目成果。 | G14: 编：Dennis Dreiskämper, Ulrike Burrmann, Miriam Kehne, Nils Neuber, Bettina Rulofs, Jessica Süßenbach, Gunda Voigts, Lena Henning | H14: Bildung und Sport | I14: Springer VS Wiesbaden | J14: 2025 | K14: 08 April 2025 | L14: 1 | M14: XIX, 249 | N14: 德文 | O14: 978-3-658-47017-3 | P14: 978-3-658-47016-6 | Q14: 10.1007/978-3-658-47017-3 | R14: https://link.springer.com/book/10.1007/978-3-658-47017-3 | S14: https://link.springer.com/content/pdf/10.1007/978-3-658-47017-3.pdf | T14: 82k | U14: Education, general; Sport Science; Sport Education and Didactics | V14: 已上线
A15: 14 | B15: 康复医学·物理治疗 | C15: 核心 | D15: Paediatric Neurorehabilitation | F15: 儿童神经康复：发育基础、运动/认知/语言/吞咽康复、脑瘫及社区康复与低资源地区实践（WFNR）。 | G15: 编：Tracey Mole, Andrea Martinuzzi | I15: Springer Cham | J15: 2026 | K15: 17 June 2026 | L15: 1 | M15: VI, 352 | N15: 英文 | O15: 978-3-032-26192-2 | P15: 978-3-032-26191-5 | Q15: 10.1007/978-3-032-26192-2 | R15: https://link.springer.com/book/10.1007/978-3-032-26192-2 | S15: https://link.springer.com/content/pdf/10.1007/978-3-032-26192-2.pdf | T15: 74k | U15: Neurology; Pediatrics | V15: 已上线
A16: 15 | B16: 康复医学·物理治疗 | C16: 核心 | D16: Kommunikation und Beziehungsgestaltung in der Physiotherapie | E16: Das Beziehungsdreieck Patient:in - Therapeut:in - Angehörige | F16: （德文）物理治疗中的沟通与关系构建：患者—治疗师—家属三角关系，含案例。 | G16: 著：Alexa von Bosse | H16: essentials | I16: Springer Berlin, Heidelberg | J16: 2026 | K16: 18 March 2026 | L16: 1 | M16: IX, 68 | N16: 德文 | O16: 978-3-662-72935-9 | P16: 978-3-662-72934-2 | Q16: 10.1007/978-3-662-72935-9 | R16: https://link.springer.com/book/10.1007/978-3-662-72935-9 | S16: https://link.springer.com/content/pdf/10.1007/978-3-662-72935-9.pdf | T16: 12k | U16: Physiotherapy; Occupational Therapy | V16: 已上线
A17: 16 | B17: 康复医学·物理治疗 | C17: 核心 | D17: Heilmittel-Report 2026 | E17: Qualität der Heilmittelversorgung | F17: （德文）2026 德国 Heilmittel 报告：物理治疗、作业治疗、言语治疗服务的质量测量与改进（22 篇专家文章）。 | G17: 编：Helmut Schröder, Christian Kopkow, Andrea Waltersbacher, Nadescha Bachayov, Jonas Schreyögg | I17: Springer Berlin, Heidelberg | J17: 2026 | K17: 27 May 2026 | L17: 1 | M17: IX, 325 | N17: 德文 | O17: 978-3-662-73466-7 | P17: 978-3-662-73465-0 | Q17: 10.1007/978-3-662-73466-7 | R17: https://link.springer.com/book/10.1007/978-3-662-73466-7 | S17: https://link.springer.com/content/pdf/10.1007/978-3-662-73466-7.pdf | T17: 39k | U17: Public Health; Health Economics; Physiotherapy; Occupational Therapy; Speech Pathology | V17: 已上线
A18: 17 | B18: 康复医学·物理治疗 | C18: 核心 | D18: Delivering Universal Health Care to People with Major Limb Loss or Damage in Low and Middle Income Countries | E18: A Complex Intervention in Uganda | F18: 中低收入国家截肢/肢体严重损伤者的假肢与康复服务：乌干达复杂干预研究。 | G18: 著：Louise Ackers, Jonathan Huck, Laurence Kenney, Allan Ndawula, Jackson Murungi | I18: Palgrave Macmillan Cham | J18: 2025 | K18: 03 April 2025 | L18: 1 | M18: XX, 229 | N18: 英文 | O18: 978-3-031-85423-1 | P18: 978-3-031-85422-4 | Q18: 10.1007/978-3-031-85423-1 | R18: https://link.springer.com/book/10.1007/978-3-031-85423-1 | S18: https://link.springer.com/content/pdf/10.1007/978-3-031-85423-1.pdf | T18: 13k | U18: Development Studies; International Relations Theory | V18: 已上线
A19: 18 | B19: 康复医学·物理治疗 | C19: 核心 | D19: Clinical Pathways in Stroke Rehabilitation | E19: Evidence-based Clinical Practice Recommendations | F19: 卒中康复临床路径：基于 RCT/系统综述的循证推荐，涵盖运动、认知、吞咽等功能障碍的评估、训练与技术辅助（WFNR）。 | G19: 编：Thomas Platz | I19: Springer Cham | J19: 2021 | K19: 14 January 2021 | L19: 1 | M19: XII, 282 | N19: 英文 | O19: 978-3-030-58505-1 | P19: 978-3-030-58504-4 | Q19: 10.1007/978-3-030-58505-1 | R19: https://link.springer.com/book/10.1007/978-3-030-58505-1 | S19: https://link.springer.com/content/pdf/10.1007/978-3-030-58505-1.pdf | T19: 372k | U19: Neurology; Physiotherapy; Neuropsychology; Nursing | V19: 已上线
A20: 19 | B20: 康复医学·物理治疗 | C20: 延伸 | D20: The Robotic Nimbus | E20: AI-Enabled Robots for Personalized Care and Human Empowerment | F20: AI 辅助机器人“Robotic Nimbus”：身体支撑、站立/行走辅助、上肢可穿戴辅助、康复与转移（即将上线）。 | G20: 编：Yasuhisa Hirata, Fumi Seto | I20: Springer Singapore | J20: 2026 | K20: 21 December 2026 | L20: 1 | M20: XIX, 382 | N20: 英文 | O20: 978-981-92-6145-1 | P20: 978-981-92-6144-4 | Q20: 10.1007/978-981-92-6145-1 | R20: https://link.springer.com/book/9789819261444 | U20: Assistive Robotics; Robotics; AI | V20: 即将上线
A21: 20 | B21: 康复医学·物理治疗 | C21: 延伸 | D21: Geriatric Surgery | F21: 老年外科：衰弱评估、预康复（prehabilitation）、围术期与术后康复方案（即将上线）。 | G21: 编：Paolo Carcoforo, Fausto Catena | H21: Updates in Surgery | I21: Springer Cham | J21: 2026 | K21: 待定 | L21: 1 | M21: X, 206 | N21: 英文 | O21: 978-3-032-24281-5 | P21: 978-3-032-24280-8 | Q21: 10.1007/978-3-032-24281-5 | R21: https://link.springer.com/book/9783032242815 | U21: Surgery; Geriatrics | V21: 即将上线
A22: 21 | B22: 康复医学·物理治疗 | C22: 延伸 | D22: Evaluation of Vocational Rehabilitation Services | E22: Return on Investment (VR-ROI) Models and Results | F22: 职业康复服务的投资回报（VR-ROI）评估：美国多州、四类残疾人群的就业结局。 | G22: 著：Christopher M. Clapp, John Pepper, Robert Schmidt, Steven Stern | H22: Diversity and Inclusion Research | I22: Springer Cham | J22: 2025 | K22: 30 May 2025 | L22: 1 | M22: XIII, 198 | N22: 英文 | O22: 978-3-031-86942-6 | P22: 978-3-031-86944-0 | Q22: 10.1007/978-3-031-86942-6 | R22: https://link.springer.com/book/10.1007/978-3-031-86942-6 | S22: https://link.springer.com/content/pdf/10.1007/978-3-031-86942-6.pdf | T22: 7.2k | U22: Human Resource Management; Services | V22: 已上线
A23: 22 | B23: 康复医学·物理治疗 | C23: 延伸 | D23: A Practical Guide on Behaviour Change Support for Self-Managing Chronic Disease | F23: 慢病自我管理的行为改变支持实用指南：体力活动、用药、饮食等行为干预技术。 | G23: 编：Mara Pereira Guerreiro, Isa Brito Félix, Marta Moreira Marques | I23: Springer Cham | J23: 2023 | K23: 07 March 2023 | L23: 1 | M23: XXVI, 122 | N23: 英文 | O23: 978-3-031-20010-6 | P23: 978-3-031-20009-0 | Q23: 10.1007/978-3-031-20010-6 | R23: https://link.springer.com/book/10.1007/978-3-031-20010-6 | S23: https://link.springer.com/content/pdf/10.1007/978-3-031-20010-6.pdf | T23: 50k | U23: Medicine/Public Health, general; Psychology; Physiology | V23: 已上线
A24: 23 | B24: 康复医学·物理治疗 | C24: 延伸 | D24: Water-filtered Infrared A (wIRA) Irradiation | E24: From Research to Clinical Settings | F24: 水滤红外线A（wIRA）照射：30 年基础与临床研究，含肌骨疾病、伤口愈合等物理因子治疗应用。 | G24: 编：Peter Vaupel | I24: Springer Cham | J24: 2022 | K24: 05 May 2022 | L24: 1 | M24: XXV, 292 | N24: 英文 | O24: 978-3-030-92880-3 | P24: 978-3-030-92879-7 | Q24: 10.1007/978-3-030-92880-3 | R24: https://link.springer.com/book/10.1007/978-3-030-92880-3 | S24: https://link.springer.com/content/pdf/10.1007/978-3-030-92880-3.pdf | T24: 136k | U24: Oncology; Surgery; Dermatology; Physiotherapy | V24: 已上线
A25: 24 | B25: 肌骨影像 | C25: 核心 | D25: Musculoskeletal Diseases 2026–2029 | E25: Diagnostic Imaging | F25: IDKD 肌骨疾病影像 2026–2029：以疾病为纲，重点 MRI/CT，含 AI 进展。 | G25: 编：Juerg Hodler, Rahel A. Kubik-Huch, Justus E. Roos | H25: IDKD Springer Series | I25: Springer Cham | J25: 2026 | K25: 26 February 2026 | L25: 1 | M25: VIII, 236 | N25: 英文 | O25: 978-3-032-17040-8 | P25: 978-3-032-17039-2 | Q25: 10.1007/978-3-032-17040-8 | R25: https://link.springer.com/book/10.1007/978-3-032-17040-8 | S25: https://link.springer.com/content/pdf/10.1007/978-3-032-17040-8.pdf | T25: 100k | U25: Imaging / Radiology; Orthopedics | V25: 已上线
A26: 25 | B26: 肌骨影像 | C26: 核心 | D26: Musculoskeletal Diseases 2021-2024 | E26: Diagnostic Imaging | F26: IDKD 肌骨疾病影像 2021–2024（上一版），含儿科肌骨影像。 | G26: 编：Juerg Hodler, Rahel A. Kubik-Huch, Gustav K. von Schulthess | H26: IDKD Springer Series | I26: Springer Cham | J26: 2021 | K26: 12 April 2021 | L26: 1 | M26: VI, 292 | N26: 英文 | O26: 978-3-030-71281-5 | P26: 978-3-030-71280-8 | Q26: 10.1007/978-3-030-71281-5 | R26: https://link.springer.com/book/10.1007/978-3-030-71281-5 | S26: https://link.springer.com/content/pdf/10.1007/978-3-030-71281-5.pdf | T26: 558k | U26: Imaging / Radiology; Orthopedics | V26: 已上线
A27: 26 | B27: 肌骨影像 | C27: 延伸 | D27: Diseases of the Brain, Head and Neck, Spine 2024-2027 | E27: Diagnostic Imaging | F27: IDKD 脑、头颈与脊柱影像 2024–2027（脊柱部分与骨科相关）。 | G27: 编：Juerg Hodler, Rahel A. Kubik-Huch, Justus E. Roos | H27: IDKD Springer Series | I27: Springer Cham | J27: 2024 | K27: 10 February 2024 | L27: 1 | M27: VI, 318 | N27: 英文 | O27: 978-3-031-50675-8 | P27: 978-3-031-50674-1 | Q27: 10.1007/978-3-031-50675-8 | R27: https://link.springer.com/book/10.1007/978-3-031-50675-8 | S27: https://link.springer.com/content/pdf/10.1007/978-3-031-50675-8.pdf | T27: 478k | U27: Imaging / Radiology; Neurology; Neurosurgery | V27: 已上线
A28: 27 | B28: 肌骨影像 | C28: 延伸 | D28: Diseases of the Brain, Head and Neck, Spine 2020–2023 | E28: Diagnostic Imaging | F28: IDKD 脑、头颈与脊柱影像 2020–2023（上一版）。 | G28: 编：Juerg Hodler, Rahel A. Kubik-Huch, Gustav K. von Schulthess | H28: IDKD Springer Series | I28: Springer Cham | J28: 2020 | K28: 14 February 2020 | L28: 1 | M28: VIII, 254 | N28: 英文 | O28: 978-3-030-38490-6 | P28: 978-3-030-38489-0 | Q28: 10.1007/978-3-030-38490-6 | R28: https://link.springer.com/book/10.1007/978-3-030-38490-6 | S28: https://link.springer.com/content/pdf/10.1007/978-3-030-38490-6.pdf | T28: 765k | U28: Imaging / Radiology; Neurology; Neurosurgery | V28: 已上线
A29: 28 | B29: 风湿·软骨·肌骨基础 | C29: 延伸 | D29: Rheumatic Diseases in the Arab World | F29: 阿拉伯世界风湿病大全（22 国）。 | G29: 编：Khalid A. Alnaqbi, Ghaydaa Aldabie | I29: Springer Singapore | J29: 2026 | K29: 11 July 2026 | L29: 1 | M29: XXVII, 635 | N29: 英文 | O29: 978-981-92-0967-5 | P29: 978-981-92-0966-8 | Q29: 10.1007/978-981-92-0967-5 | R29: https://link.springer.com/book/10.1007/978-981-92-0967-5 | S29: https://link.springer.com/content/pdf/10.1007/978-981-92-0967-5.pdf | T29: 50k | U29: Rheumatology; Internal Medicine; Immunology | V29: 已上线
A30: 29 | B30: 风湿·软骨·肌骨基础 | C30: 延伸 | D30: Electromechanobiology of Cartilage and Osteoarthritis | E30: A Tribute to Alan Grodzinsky on his 75th Birthday | F30: 软骨电-力学生物学与骨关节炎：组织力学、机械生物学及 OA 发病与治疗进展。 | G30: 编：Brianne K. Connizzo, Lin Han, Robert L. Sah | H30: Advances in Experimental Medicine and Biology | I30: Springer Cham | J30: 2023 | K30: 13 April 2023 | L30: 1 | M30: XIV, 173 | N30: 英文 | O30: 978-3-031-25588-5 | P30: 978-3-031-25590-8 | Q30: 10.1007/978-3-031-25588-5 | R30: https://link.springer.com/book/10.1007/978-3-031-25588-5 | S30: https://link.springer.com/content/pdf/10.1007/978-3-031-25588-5.pdf | T30: 50k | U30: Biomechanics; Biomedical Engineering and Bioengineering | V30: 已上线
A31: 30 | B31: 风湿·软骨·肌骨基础 | C31: 延伸 | D31: Axial Spondyloarthritis: Patient-Reported Impact in Europe | F31: 中轴型脊柱关节炎对欧洲患者的影响（IMAS 调查，2000+ 患者）。 | G31: 著：Marco Garrido-Cumbrera, Victoria Navarro-Compán, Christine Bundy, Raj Mahapatra, Souzi Makri, Carlos J. Delgado-Domínguez, Pedro Plazuelo-Ramos, Denis Poddubnyy | I31: Springer Cham | J31: 2022 | K31: 31 August 2022 | L31: 1 | M31: XXI, 109 | N31: 英文 | O31: 978-3-030-97606-4 | P31: 978-3-030-97605-7 | Q31: 10.1007/978-3-030-97606-4 | R31: https://link.springer.com/book/10.1007/978-3-030-97606-4 | S31: https://link.springer.com/content/pdf/10.1007/978-3-030-97606-4.pdf | T31: 28k | U31: Rheumatology | V31: 已上线
A32: 31 | B32: 风湿·软骨·肌骨基础 | C32: 延伸 | D32: Skills in Rheumatology | F32: 风湿病临床技能：强调详细的肌肉骨骼查体与常见风湿病处理。 | G32: 编：Hani Almoallim, Mohamed Cheikh | I32: Springer Singapore | J32: 2021 | K32: 05 January 2021 | L32: 1 | M32: XIII, 566 | N32: 英文 | O32: 978-981-15-8323-0 | P32: 978-981-15-8322-3 | Q32: 10.1007/978-981-15-8323-0 | R32: https://link.springer.com/book/10.1007/978-981-15-8323-0 | S32: https://link.springer.com/content/pdf/10.1007/978-981-15-8323-0.pdf | T32: 737k | U32: Rheumatology | V32: 已上线

Sheet 分类统计
A1: 按类别统计（公式引用“书目汇总”）
A3: 类别 | B3: 图书总数 | C3: 核心 | D3: 延伸 | E3: 英文 | F3: 德文 | G3: 最早版权年 | H3: 最新版权年
A4: 骨科·骨折·关节 | B4: =COUNTIF('书目汇总'!$B$2:$B$32,A4) | C4: =COUNTIFS('书目汇总'!$B$2:$B$32,A4,'书目汇总'!$C$2:$C$32,"核心") | D4: =COUNTIFS('书目汇总'!$B$2:$B$32,A4,'书目汇总'!$C$2:$C$32,"延伸") | E4: =COUNTIFS('书目汇总'!$B$2:$B$32,A4,'书目汇总'!$N$2:$N$32,"英文") | F4: =COUNTIFS('书目汇总'!$B$2:$B$32,A4,'书目汇总'!$N$2:$N$32,"德文") | G4: =_xlfn.MINIFS('书目汇总'!$J$2:$J$32,'书目汇总'!$B$2:$B$32,A4) | H4: =_xlfn.MAXIFS('书目汇总'!$J$2:$J$32,'书目汇总'!$B$2:$B$32,A4)
A5: 创伤医学 | B5: =COUNTIF('书目汇总'!$B$2:$B$32,A5) | C5: =COUNTIFS('书目汇总'!$B$2:$B$32,A5,'书目汇总'!$C$2:$C$32,"核心") | D5: =COUNTIFS('书目汇总'!$B$2:$B$32,A5,'书目汇总'!$C$2:$C$32,"延伸") | E5: =COUNTIFS('书目汇总'!$B$2:$B$32,A5,'书目汇总'!$N$2:$N$32,"英文") | F5: =COUNTIFS('书目汇总'!$B$2:$B$32,A5,'书目汇总'!$N$2:$N$32,"德文") | G5: =_xlfn.MINIFS('书目汇总'!$J$2:$J$32,'书目汇总'!$B$2:$B$32,A5) | H5: =_xlfn.MAXIFS('书目汇总'!$J$2:$J$32,'书目汇总'!$B$2:$B$32,A5)
A6: 运动医学·运动损伤 | B6: =COUNTIF('书目汇总'!$B$2:$B$32,A6) | C6: =COUNTIFS('书目汇总'!$B$2:$B$32,A6,'书目汇总'!$C$2:$C$32,"核心") | D6: =COUNTIFS('书目汇总'!$B$2:$B$32,A6,'书目汇总'!$C$2:$C$32,"延伸") | E6: =COUNTIFS('书目汇总'!$B$2:$B$32,A6,'书目汇总'!$N$2:$N$32,"英文") | F6: =COUNTIFS('书目汇总'!$B$2:$B$32,A6,'书目汇总'!$N$2:$N$32,"德文") | G6: =_xlfn.MINIFS('书目汇总'!$J$2:$J$32,'书目汇总'!$B$2:$B$32,A6) | H6: =_xlfn.MAXIFS('书目汇总'!$J$2:$J$32,'书目汇总'!$B$2:$B$32,A6)
A7: 运动医学·运动科学 | B7: =COUNTIF('书目汇总'!$B$2:$B$32,A7) | C7: =COUNTIFS('书目汇总'!$B$2:$B$32,A7,'书目汇总'!$C$2:$C$32,"核心") | D7: =COUNTIFS('书目汇总'!$B$2:$B$32,A7,'书目汇总'!$C$2:$C$32,"延伸") | E7: =COUNTIFS('书目汇总'!$B$2:$B$32,A7,'书目汇总'!$N$2:$N$32,"英文") | F7: =COUNTIFS('书目汇总'!$B$2:$B$32,A7,'书目汇总'!$N$2:$N$32,"德文") | G7: =_xlfn.MINIFS('书目汇总'!$J$2:$J$32,'书目汇总'!$B$2:$B$32,A7) | H7: =_xlfn.MAXIFS('书目汇总'!$J$2:$J$32,'书目汇总'!$B$2:$B$32,A7)
A8: 运动训练·运动科学 | B8: =COUNTIF('书目汇总'!$B$2:$B$32,A8) | C8: =COUNTIFS('书目汇总'!$B$2:$B$32,A8,'书目汇总'!$C$2:$C$32,"核心") | D8: =COUNTIFS('书目汇总'!$B$2:$B$32,A8,'书目汇总'!$C$2:$C$32,"延伸") | E8: =COUNTIFS('书目汇总'!$B$2:$B$32,A8,'书目汇总'!$N$2:$N$32,"英文") | F8: =COUNTIFS('书目汇总'!$B$2:$B$32,A8,'书目汇总'!$N$2:$N$32,"德文") | G8: =_xlfn.MINIFS('书目汇总'!$J$2:$J$32,'书目汇总'!$B$2:$B$32,A8) | H8: =_xlfn.MAXIFS('书目汇总'!$J$2:$J$32,'书目汇总'!$B$2:$B$32,A8)
A9: 康复医学·物理治疗 | B9: =COUNTIF('书目汇总'!$B$2:$B$32,A9) | C9: =COUNTIFS('书目汇总'!$B$2:$B$32,A9,'书目汇总'!$C$2:$C$32,"核心") | D9: =COUNTIFS('书目汇总'!$B$2:$B$32,A9,'书目汇总'!$C$2:$C$32,"延伸") | E9: =COUNTIFS('书目汇总'!$B$2:$B$32,A9,'书目汇总'!$N$2:$N$32,"英文") | F9: =COUNTIFS('书目汇总'!$B$2:$B$32,A9,'书目汇总'!$N$2:$N$32,"德文") | G9: =_xlfn.MINIFS('书目汇总'!$J$2:$J$32,'书目汇总'!$B$2:$B$32,A9) | H9: =_xlfn.MAXIFS('书目汇总'!$J$2:$J$32,'书目汇总'!$B$2:$B$32,A9)
A10: 肌骨影像 | B10: =COUNTIF('书目汇总'!$B$2:$B$32,A10) | C10: =COUNTIFS('书目汇总'!$B$2:$B$32,A10,'书目汇总'!$C$2:$C$32,"核心") | D10: =COUNTIFS('书目汇总'!$B$2:$B$32,A10,'书目汇总'!$C$2:$C$32,"延伸") | E10: =COUNTIFS('书目汇总'!$B$2:$B$32,A10,'书目汇总'!$N$2:$N$32,"英文") | F10: =COUNTIFS('书目汇总'!$B$2:$B$32,A10,'书目汇总'!$N$2:$N$32,"德文") | G10: =_xlfn.MINIFS('书目汇总'!$J$2:$J$32,'书目汇总'!$B$2:$B$32,A10) | H10: =_xlfn.MAXIFS('书目汇总'!$J$2:$J$32,'书目汇总'!$B$2:$B$32,A10)
A11: 风湿·软骨·肌骨基础 | B11: =COUNTIF('书目汇总'!$B$2:$B$32,A11) | C11: =COUNTIFS('书目汇总'!$B$2:$B$32,A11,'书目汇总'!$C$2:$C$32,"核心") | D11: =COUNTIFS('书目汇总'!$B$2:$B$32,A11,'书目汇总'!$C$2:$C$32,"延伸") | E11: =COUNTIFS('书目汇总'!$B$2:$B$32,A11,'书目汇总'!$N$2:$N$32,"英文") | F11: =COUNTIFS('书目汇总'!$B$2:$B$32,A11,'书目汇总'!$N$2:$N$32,"德文") | G11: =_xlfn.MINIFS('书目汇总'!$J$2:$J$32,'书目汇总'!$B$2:$B$32,A11) | H11: =_xlfn.MAXIFS('书目汇总'!$J$2:$J$32,'书目汇总'!$B$2:$B$32,A11)
A12: 合计 | B12: =SUM(B4:B11) | C12: =SUM(C4:C11) | D12: =SUM(D4:D11) | E12: =SUM(E4:E11) | F12: =SUM(F4:F11) | G12: =MIN(G4:G11) | H12: =MAX(H4:H11)

Sheet 检索说明
A1: 检索说明
A2: 数据来源 | B2: Springer Nature Link 官方检索（link.springer.com/search），筛选“内容类型=Book”+“出版模式=Open access”；详细书目信息取自各书官方页面“Bibliographic information”。
A3: 检索日期 | B3: 2026-09-23
A4: 检索策略 | B4: ① 学科分面：Medicine & Public Health 下全部开放获取图书（共 214 本）逐条人工筛选；② 子学科分面：Orthopedics、Surgical Orthopedics、Sports Medicine、Physiotherapy、Sport Science、Rehabilitation、Traumatic Surgery；③ 跨学科关键词（中英德）：rehabilitation、physiotherapy、sport(s)、exercise、injury、fracture、trauma、musculoskeletal、orthopedic、prosthesis、exoskeleton、gait、spine、athlete、physical activity、osteoarthritis、arthroplasty、Bewegung、Sportmedizin、Orthopädie、Unfallchirurgie 等。
A5: 筛选结果 | B5: 共 31 本：核心 17 本（直接对应骨科/创伤/运动医学/康复/物理治疗）、延伸 14 本（肌骨影像、风湿、辅助机器人、运动数据分析等相关领域）。
A6: 相关度 | B6: 核心 = 主题直接属于骨科、创伤医学、运动医学、康复医学、物理治疗、运动训练；延伸 = 交叉或相关领域，可作补充阅读。
A7: 下载方式 | B7: “PDF 全书下载”列为官方全书 PDF 链接（开放获取，免费）；部分书亦提供 EPUB。“即将上线”的 2 本目前页面已标注 Open Access，但全文尚未开放。
A8: 重要发现 | B8: Springer 在这些领域的开放获取图书数量有限：Traumatic Surgery 与 Rehabilitation Medicine 子学科下开放获取图书为 0；许多常见骨科/运动医学书（如 ESSKA 系列、Senior Trauma Patients 等）为付费书，未收录。
A9: 字段说明 | B9: 版权年取自检索结果；在线出版日期取自书页 eBook 发布日期；访问量为抓取当日书页显示值，会持续变化。
A10: 局限 | B10: Springer Link 的开放获取标记与学科标注由出版社维护，个别书可能漏标；本表仅收录 Springer Nature 旗下（Springer / Springer VS / Palgrave）图书，不含期刊文章与单独开放的章节。
